Metadata-Version: 1.1
Name: ms-to-datetime
Version: 0.0.2
Summary: Convert from ms to datetime
Home-page: UNKNOWN
Author: Felipe Viana
Author-email: UNKNOWN
License: MIT
Platform: UNKNOWN
Classifier: Programming Language :: Python :: 3
Classifier: License :: OSI Approved :: MIT License
Classifier: Operating System :: OS Independent
